repo2pdf/__init__.py
repo2pdf/cli.py
repo2pdf/core.py
repo2pdf/pdf.py
repo2pdf/utils.py
tests/__init__.py
tests/test_core.py
tests/test_pdf.py
tests/test_utils.py
repo2pdf-0.1.5.dist-info/METADATA
repo2pdf-0.1.5.dist-info/WHEEL
repo2pdf-0.1.5.dist-info/entry_points.txt
repo2pdf-0.1.5.dist-info/top_level.txt
repo2pdf-0.1.5.dist-info/RECORD
