Metadata-Version: 2.4
Name: repo2pdf
Version: 0.1.5
Summary: Convert coding repositories into PDFs and JSON summaries
Author-email: Haris Sujethan <your-email@example.com>
License: MIT
Requires-Python: >=3.7
Requires-Dist: fpdf2
Requires-Dist: GitPython
Requires-Dist: inquirer
Requires-Dist: pathspec
